hlunity/__init__.py
hlunity-1.6.dist-info/METADATA
hlunity-1.6.dist-info/WHEEL
hlunity-1.6.dist-info/top_level.txt
hlunity-1.6.dist-info/RECORD
